__init__.py
sinapsis_langchain_splitters/helpers/__init__.py
sinapsis_langchain_splitters/helpers/tags.py
sinapsis_langchain_splitters/templates/__init__.py
sinapsis_langchain_splitters/templates/langchain_text_splitters.py
sinapsis_langchain_splitters-0.1.5.dist-info/METADATA
sinapsis_langchain_splitters-0.1.5.dist-info/WHEEL
sinapsis_langchain_splitters-0.1.5.dist-info/top_level.txt
sinapsis_langchain_splitters-0.1.5.dist-info/RECORD
