Metadata-Version: 2.4
Name: sinapsis-langchain-splitters
Version: 0.1.5
Summary: Add your description here
Author-email: SinapsisAI <dev@sinapsis.tech>
Project-URL: Homepage, https://sinapsis.tech
Project-URL: Documentation, https://docs.sinapsis.tech/docs
Project-URL: Tutorials, https://docs.sinapsis.tech/tutorials
Project-URL: Repository, https://github.com/Sinapsis-AI/sinapsis-langchain.git
Requires-Python: >=3.10
Requires-Dist: langchain-community>=0.3.20
Requires-Dist: langchain-text-splitters>=0.3.7
Requires-Dist: sinapsis>=0.1.1
